{
  "schema_version": "advanced_signal_quality_v1",
  "generated_at": "2026-05-19T05:25:44.187563+00:00",
  "status": "PASS",
  "signal_source": "docs/data/prediction_engine/signal_dashboard_news_enriched.json",
  "market_rows_loaded": 79,
  "counts": {
    "signals": 50,
    "quality_approved": 0,
    "quality_blocked": 0,
    "dashboard_only_or_caution": 50
  },
  "market_regime": {
    "regime": "NEUTRAL",
    "market_regime_score": 0,
    "details": {}
  },
  "theme_stats": {
    "small_cap_ai": {
      "members": [
        "PATH",
        "PLTR",
        "AI",
        "SOUN",
        "BBAI"
      ],
      "avg_day_change": -0.062,
      "count": 5,
      "sympathy_score": 3
    },
    "space_air": {
      "members": [
        "ASTS",
        "RKLB",
        "LUNR",
        "ACHR"
      ],
      "avg_day_change": -0.365,
      "count": 4,
      "sympathy_score": 3
    },
    "ev": {
      "members": [
        "LCID",
        "RIVN",
        "GM",
        "F",
        "NIO",
        "LI"
      ],
      "avg_day_change": 0.1617,
      "count": 6,
      "sympathy_score": 3
    },
    "quantum": {
      "members": [
        "IONQ",
        "QBTS"
      ],
      "avg_day_change": 0.085,
      "count": 2,
      "sympathy_score": 3
    },
    "travel_reopen": {
      "members": [
        "DAL",
        "NCLH"
      ],
      "avg_day_change": 0.22,
      "count": 2,
      "sympathy_score": 3
    },
    "crypto": {
      "members": [
        "COIN",
        "MARA",
        "MSTR",
        "WULF"
      ],
      "avg_day_change": 0.0925,
      "count": 4,
      "sympathy_score": 3
    },
    "meme_retail": {
      "members": [
        "BYND",
        "GME"
      ],
      "avg_day_change": -0.035,
      "count": 2,
      "sympathy_score": 3
    },
    "mega_cap_ai": {
      "members": [
        "META",
        "GOOG",
        "AMZN",
        "MSFT"
      ],
      "avg_day_change": 0.005,
      "count": 4,
      "sympathy_score": 3
    },
    "fintech": {
      "members": [
        "UPST"
      ],
      "avg_day_change": -0.18,
      "count": 1,
      "sympathy_score": 0
    }
  },
  "rows": [
    {
      "ticker": "PLTR",
      "status": "ALERT_ONLY",
      "quality_gate_status": "DASHBOARD_ONLY",
      "advanced_quality": {
        "advanced_quality_score": 92.25,
        "spread_pct": 0.0817,
        "dollar_volume": 7141834.95,
        "spread_score": 15.0,
        "liquidity_score": 12.0,
        "rvol_quality_score": 2.0,
        "vwap_control_score": 18.0,
        "anti_chase_score": 18.0,
        "pullback_quality_score": 18,
        "breakout_compression_score": 10.0,
        "sympathy_score": 3,
        "theme": "small_cap_ai",
        "halt_risk_score": 15.0,
        "market_regime": "NEUTRAL",
        "reasons": [
          "spread_tight",
          "good_dollar_volume",
          "weak_rvol",
          "vwap_controlled",
          "not_chasing_vwap_controlled",
          "near_vwap_pullback_zone",
          "volume_returning",
          "breakout_not_overextended",
          "breakout_volume_acceleration",
          "volume_ignition_halt_risk"
        ],
        "hard_blocks": [],
        "quality_gate_status": "DASHBOARD_ONLY",
        "quality_gate_blocks": [
          "base_status_not_trade_eligible:ALERT_ONLY"
        ]
      }
    },
    {
      "ticker": "IONQ",
      "status": "ALERT_ONLY",
      "quality_gate_status": "DASHBOARD_ONLY",
      "advanced_quality": {
        "advanced_quality_score": 91.0,
        "spread_pct": 0.2437,
        "dollar_volume": 1367200.85,
        "spread_score": 15.0,
        "liquidity_score": 7.0,
        "rvol_quality_score": 2.0,
        "vwap_control_score": 18.0,
        "anti_chase_score": 18.0,
        "pullback_quality_score": 18,
        "breakout_compression_score": 10.0,
        "sympathy_score": 3,
        "theme": "quantum",
        "halt_risk_score": 0,
        "market_regime": "NEUTRAL",
        "reasons": [
          "spread_tight",
          "thin_but_tradeable_dollar_volume",
          "weak_rvol",
          "vwap_controlled",
          "not_chasing_vwap_controlled",
          "near_vwap_pullback_zone",
          "volume_returning",
          "breakout_not_overextended",
          "breakout_volume_acceleration"
        ],
        "hard_blocks": [],
        "quality_gate_status": "DASHBOARD_ONLY",
        "quality_gate_blocks": [
          "base_status_not_trade_eligible:ALERT_ONLY"
        ]
      }
    },
    {
      "ticker": "RIVN",
      "status": "ALERT_ONLY",
      "quality_gate_status": "DASHBOARD_ONLY",
      "advanced_quality": {
        "advanced_quality_score": 91.0,
        "spread_pct": 0.1493,
        "dollar_volume": 1371918.8,
        "spread_score": 15.0,
        "liquidity_score": 7.0,
        "rvol_quality_score": 2.0,
        "vwap_control_score": 18.0,
        "anti_chase_score": 18.0,
        "pullback_quality_score": 18,
        "breakout_compression_score": 10.0,
        "sympathy_score": 3,
        "theme": "ev",
        "halt_risk_score": 0,
        "market_regime": "NEUTRAL",
        "reasons": [
          "spread_tight",
          "thin_but_tradeable_dollar_volume",
          "weak_rvol",
          "vwap_controlled",
          "not_chasing_vwap_controlled",
          "near_vwap_pullback_zone",
          "volume_returning",
          "breakout_not_overextended",
          "breakout_volume_acceleration"
        ],
        "hard_blocks": [],
        "quality_gate_status": "DASHBOARD_ONLY",
        "quality_gate_blocks": [
          "base_status_not_trade_eligible:ALERT_ONLY"
        ]
      }
    },
    {
      "ticker": "AAPL",
      "status": "ALERT_ONLY",
      "quality_gate_status": "DASHBOARD_ONLY",
      "advanced_quality": {
        "advanced_quality_score": 84.25,
        "spread_pct": 0.0672,
        "dollar_volume": 3379215.84,
        "spread_score": 15.0,
        "liquidity_score": 7.0,
        "rvol_quality_score": 2.0,
        "vwap_control_score": 18.0,
        "anti_chase_score": 18.0,
        "pullback_quality_score": 18,
        "breakout_compression_score": 10.0,
        "sympathy_score": 0,
        "theme": null,
        "halt_risk_score": 15.0,
        "market_regime": "NEUTRAL",
        "reasons": [
          "spread_tight",
          "thin_but_tradeable_dollar_volume",
          "weak_rvol",
          "vwap_controlled",
          "not_chasing_vwap_controlled",
          "near_vwap_pullback_zone",
          "volume_returning",
          "breakout_not_overextended",
          "breakout_volume_acceleration",
          "volume_ignition_halt_risk"
        ],
        "hard_blocks": [],
        "quality_gate_status": "DASHBOARD_ONLY",
        "quality_gate_blocks": [
          "base_status_not_trade_eligible:ALERT_ONLY"
        ]
      }
    },
    {
      "ticker": "PATH",
      "status": "ALERT_ONLY",
      "quality_gate_status": "DASHBOARD_ONLY",
      "advanced_quality": {
        "advanced_quality_score": 84.0,
        "spread_pct": 0.4684,
        "dollar_volume": 278163.3,
        "spread_score": 15.0,
        "liquidity_score": 0.0,
        "rvol_quality_score": 2.0,
        "vwap_control_score": 18.0,
        "anti_chase_score": 18.0,
        "pullback_quality_score": 18,
        "breakout_compression_score": 10.0,
        "sympathy_score": 3,
        "theme": "small_cap_ai",
        "halt_risk_score": 0,
        "market_regime": "NEUTRAL",
        "reasons": [
          "spread_tight",
          "dollar_volume_too_low",
          "weak_rvol",
          "vwap_controlled",
          "not_chasing_vwap_controlled",
          "near_vwap_pullback_zone",
          "volume_returning",
          "breakout_not_overextended",
          "breakout_volume_acceleration"
        ],
        "hard_blocks": [],
        "quality_gate_status": "DASHBOARD_ONLY",
        "quality_gate_blocks": [
          "base_status_not_trade_eligible:ALERT_ONLY",
          "dollar_volume_below_1m"
        ]
      }
    },
    {
      "ticker": "ASTS",
      "status": "ALERT_ONLY",
      "quality_gate_status": "DASHBOARD_ONLY",
      "advanced_quality": {
        "advanced_quality_score": 84.0,
        "spread_pct": 0.0688,
        "dollar_volume": 4274162.1,
        "spread_score": 15.0,
        "liquidity_score": 7.0,
        "rvol_quality_score": 2.0,
        "vwap_control_score": 18.0,
        "anti_chase_score": 18.0,
        "pullback_quality_score": 15.0,
        "breakout_compression_score": 6.0,
        "sympathy_score": 3,
        "theme": "space_air",
        "halt_risk_score": 0,
        "market_regime": "NEUTRAL",
        "reasons": [
          "spread_tight",
          "thin_but_tradeable_dollar_volume",
          "weak_rvol",
          "vwap_controlled",
          "not_chasing_vwap_controlled",
          "near_vwap_pullback_zone",
          "breakout_not_overextended"
        ],
        "hard_blocks": [],
        "quality_gate_status": "DASHBOARD_ONLY",
        "quality_gate_blocks": [
          "base_status_not_trade_eligible:ALERT_ONLY"
        ]
      }
    },
    {
      "ticker": "LCID",
      "status": "ALERT_ONLY",
      "quality_gate_status": "DASHBOARD_ONLY",
      "advanced_quality": {
        "advanced_quality_score": 84.0,
        "spread_pct": 0.3472,
        "dollar_volume": 445040.1,
        "spread_score": 15.0,
        "liquidity_score": 0.0,
        "rvol_quality_score": 2.0,
        "vwap_control_score": 18.0,
        "anti_chase_score": 18.0,
        "pullback_quality_score": 18,
        "breakout_compression_score": 10.0,
        "sympathy_score": 3,
        "theme": "ev",
        "halt_risk_score": 0,
        "market_regime": "NEUTRAL",
        "reasons": [
          "spread_tight",
          "dollar_volume_too_low",
          "weak_rvol",
          "vwap_controlled",
          "not_chasing_vwap_controlled",
          "near_vwap_pullback_zone",
          "volume_returning",
          "breakout_not_overextended",
          "breakout_volume_acceleration"
        ],
        "hard_blocks": [],
        "quality_gate_status": "DASHBOARD_ONLY",
        "quality_gate_blocks": [
          "base_status_not_trade_eligible:ALERT_ONLY",
          "dollar_volume_below_1m"
        ]
      }
    },
    {
      "ticker": "COIN",
      "status": "WATCH_ONLY",
      "quality_gate_status": "DASHBOARD_ONLY",
      "advanced_quality": {
        "advanced_quality_score": 84.0,
        "spread_pct": 0.1582,
        "dollar_volume": 2623673.25,
        "spread_score": 15.0,
        "liquidity_score": 7.0,
        "rvol_quality_score": 2.0,
        "vwap_control_score": 18.0,
        "anti_chase_score": 18.0,
        "pullback_quality_score": 15.0,
        "breakout_compression_score": 6.0,
        "sympathy_score": 3,
        "theme": "crypto",
        "halt_risk_score": 0,
        "market_regime": "NEUTRAL",
        "reasons": [
          "spread_tight",
          "thin_but_tradeable_dollar_volume",
          "weak_rvol",
          "vwap_controlled",
          "not_chasing_vwap_controlled",
          "near_vwap_pullback_zone",
          "breakout_not_overextended"
        ],
        "hard_blocks": [],
        "quality_gate_status": "DASHBOARD_ONLY",
        "quality_gate_blocks": [
          "base_status_not_trade_eligible:WATCH_ONLY"
        ]
      }
    },
    {
      "ticker": "ORCL",
      "status": "WATCH_ONLY",
      "quality_gate_status": "DASHBOARD_ONLY",
      "advanced_quality": {
        "advanced_quality_score": 81.0,
        "spread_pct": 0.0268,
        "dollar_volume": 5235144.34,
        "spread_score": 15.0,
        "liquidity_score": 12.0,
        "rvol_quality_score": 2.0,
        "vwap_control_score": 18.0,
        "anti_chase_score": 13.0,
        "pullback_quality_score": 15.0,
        "breakout_compression_score": 6.0,
        "sympathy_score": 0,
        "theme": null,
        "halt_risk_score": 0,
        "market_regime": "NEUTRAL",
        "reasons": [
          "spread_tight",
          "good_dollar_volume",
          "weak_rvol",
          "vwap_controlled",
          "not_chasing_vwap_controlled",
          "volume_fading",
          "near_vwap_pullback_zone",
          "breakout_not_overextended"
        ],
        "hard_blocks": [],
        "quality_gate_status": "DASHBOARD_ONLY",
        "quality_gate_blocks": [
          "base_status_not_trade_eligible:WATCH_ONLY"
        ]
      }
    },
    {
      "ticker": "F",
      "status": "WATCH_ONLY",
      "quality_gate_status": "DASHBOARD_ONLY",
      "advanced_quality": {
        "advanced_quality_score": 79.0,
        "spread_pct": 0.3824,
        "dollar_volume": 1240129.19,
        "spread_score": 15.0,
        "liquidity_score": 7.0,
        "rvol_quality_score": 2.0,
        "vwap_control_score": 18.0,
        "anti_chase_score": 13.0,
        "pullback_quality_score": 15.0,
        "breakout_compression_score": 6.0,
        "sympathy_score": 3,
        "theme": "ev",
        "halt_risk_score": 0,
        "market_regime": "NEUTRAL",
        "reasons": [
          "spread_tight",
          "thin_but_tradeable_dollar_volume",
          "weak_rvol",
          "vwap_controlled",
          "not_chasing_vwap_controlled",
          "volume_fading",
          "near_vwap_pullback_zone",
          "breakout_not_overextended"
        ],
        "hard_blocks": [],
        "quality_gate_status": "DASHBOARD_ONLY",
        "quality_gate_blocks": [
          "base_status_not_trade_eligible:WATCH_ONLY"
        ]
      }
    },
    {
      "ticker": "MARA",
      "status": "WATCH_ONLY",
      "quality_gate_status": "DASHBOARD_ONLY",
      "advanced_quality": {
        "advanced_quality_score": 79.0,
        "spread_pct": 0.33,
        "dollar_volume": 1048592.5,
        "spread_score": 15.0,
        "liquidity_score": 7.0,
        "rvol_quality_score": 2.0,
        "vwap_control_score": 18.0,
        "anti_chase_score": 13.0,
        "pullback_quality_score": 15.0,
        "breakout_compression_score": 6.0,
        "sympathy_score": 3,
        "theme": "crypto",
        "halt_risk_score": 0,
        "market_regime": "NEUTRAL",
        "reasons": [
          "spread_tight",
          "thin_but_tradeable_dollar_volume",
          "weak_rvol",
          "vwap_controlled",
          "not_chasing_vwap_controlled",
          "volume_fading",
          "near_vwap_pullback_zone",
          "breakout_not_overextended"
        ],
        "hard_blocks": [],
        "quality_gate_status": "DASHBOARD_ONLY",
        "quality_gate_blocks": [
          "base_status_not_trade_eligible:WATCH_ONLY"
        ]
      }
    },
    {
      "ticker": "GM",
      "status": "WATCH_ONLY",
      "quality_gate_status": "DASHBOARD_ONLY",
      "advanced_quality": {
        "advanced_quality_score": 77.0,
        "spread_pct": 0.2321,
        "dollar_volume": 67463.51,
        "spread_score": 15.0,
        "liquidity_score": 0.0,
        "rvol_quality_score": 2.0,
        "vwap_control_score": 18.0,
        "anti_chase_score": 18.0,
        "pullback_quality_score": 15.0,
        "breakout_compression_score": 6.0,
        "sympathy_score": 3,
        "theme": "ev",
        "halt_risk_score": 0,
        "market_regime": "NEUTRAL",
        "reasons": [
          "spread_tight",
          "dollar_volume_too_low",
          "weak_rvol",
          "vwap_controlled",
          "not_chasing_vwap_controlled",
          "near_vwap_pullback_zone",
          "breakout_not_overextended"
        ],
        "hard_blocks": [],
        "quality_gate_status": "DASHBOARD_ONLY",
        "quality_gate_blocks": [
          "base_status_not_trade_eligible:WATCH_ONLY",
          "dollar_volume_below_1m"
        ]
      }
    },
    {
      "ticker": "NCLH",
      "status": "WATCH_ONLY",
      "quality_gate_status": "DASHBOARD_ONLY",
      "advanced_quality": {
        "advanced_quality_score": 77.0,
        "spread_pct": 0.4571,
        "dollar_volume": 331398.0,
        "spread_score": 15.0,
        "liquidity_score": 0.0,
        "rvol_quality_score": 2.0,
        "vwap_control_score": 18.0,
        "anti_chase_score": 18.0,
        "pullback_quality_score": 15.0,
        "breakout_compression_score": 6.0,
        "sympathy_score": 3,
        "theme": "travel_reopen",
        "halt_risk_score": 0,
        "market_regime": "NEUTRAL",
        "reasons": [
          "spread_tight",
          "dollar_volume_too_low",
          "weak_rvol",
          "vwap_controlled",
          "not_chasing_vwap_controlled",
          "near_vwap_pullback_zone",
          "breakout_not_overextended"
        ],
        "hard_blocks": [],
        "quality_gate_status": "DASHBOARD_ONLY",
        "quality_gate_blocks": [
          "base_status_not_trade_eligible:WATCH_ONLY",
          "dollar_volume_below_1m"
        ]
      }
    },
    {
      "ticker": "AI",
      "status": "WATCH_ONLY",
      "quality_gate_status": "DASHBOARD_ONLY",
      "advanced_quality": {
        "advanced_quality_score": 77.0,
        "spread_pct": 0.3423,
        "dollar_volume": 39954.36,
        "spread_score": 15.0,
        "liquidity_score": 0.0,
        "rvol_quality_score": 2.0,
        "vwap_control_score": 18.0,
        "anti_chase_score": 18.0,
        "pullback_quality_score": 15.0,
        "breakout_compression_score": 6.0,
        "sympathy_score": 3,
        "theme": "small_cap_ai",
        "halt_risk_score": 0,
        "market_regime": "NEUTRAL",
        "reasons": [
          "spread_tight",
          "dollar_volume_too_low",
          "weak_rvol",
          "vwap_controlled",
          "not_chasing_vwap_controlled",
          "near_vwap_pullback_zone",
          "breakout_not_overextended"
        ],
        "hard_blocks": [],
        "quality_gate_status": "DASHBOARD_ONLY",
        "quality_gate_blocks": [
          "base_status_not_trade_eligible:WATCH_ONLY",
          "dollar_volume_below_1m"
        ]
      }
    },
    {
      "ticker": "BYND",
      "status": "WATCH_ONLY",
      "quality_gate_status": "DASHBOARD_ONLY",
      "advanced_quality": {
        "advanced_quality_score": 76.5,
        "spread_pct": 0.144,
        "dollar_volume": 77348.87,
        "spread_score": 15.0,
        "liquidity_score": 0.0,
        "rvol_quality_score": 2.0,
        "vwap_control_score": 18.0,
        "anti_chase_score": 18.0,
        "pullback_quality_score": 18,
        "breakout_compression_score": 10.0,
        "sympathy_score": 3,
        "theme": "meme_retail",
        "halt_risk_score": 30.0,
        "market_regime": "NEUTRAL",
        "reasons": [
          "spread_tight",
          "dollar_volume_too_low",
          "weak_rvol",
          "vwap_controlled",
          "not_chasing_vwap_controlled",
          "near_vwap_pullback_zone",
          "volume_returning",
          "breakout_not_overextended",
          "breakout_volume_acceleration",
          "volume_ignition_halt_risk",
          "low_price_halt_risk"
        ],
        "hard_blocks": [],
        "quality_gate_status": "DASHBOARD_ONLY",
        "quality_gate_blocks": [
          "base_status_not_trade_eligible:WATCH_ONLY",
          "dollar_volume_below_1m"
        ]
      }
    },
    {
      "ticker": "PINS",
      "status": "WATCH_ONLY",
      "quality_gate_status": "DASHBOARD_ONLY",
      "advanced_quality": {
        "advanced_quality_score": 74.0,
        "spread_pct": 0.451,
        "dollar_volume": 11812.8,
        "spread_score": 15.0,
        "liquidity_score": 0.0,
        "rvol_quality_score": 2.0,
        "vwap_control_score": 18.0,
        "anti_chase_score": 18.0,
        "pullback_quality_score": 15.0,
        "breakout_compression_score": 6.0,
        "sympathy_score": 0,
        "theme": null,
        "halt_risk_score": 0,
        "market_regime": "NEUTRAL",
        "reasons": [
          "spread_tight",
          "dollar_volume_too_low",
          "weak_rvol",
          "vwap_controlled",
          "not_chasing_vwap_controlled",
          "near_vwap_pullback_zone",
          "breakout_not_overextended"
        ],
        "hard_blocks": [],
        "quality_gate_status": "DASHBOARD_ONLY",
        "quality_gate_blocks": [
          "base_status_not_trade_eligible:WATCH_ONLY",
          "dollar_volume_below_1m"
        ]
      }
    },
    {
      "ticker": "PANW",
      "status": "NO_TRADE",
      "quality_gate_status": "DASHBOARD_ONLY",
      "advanced_quality": {
        "advanced_quality_score": 74.0,
        "spread_pct": 0.1614,
        "dollar_volume": 422751.34,
        "spread_score": 15.0,
        "liquidity_score": 0.0,
        "rvol_quality_score": 2.0,
        "vwap_control_score": 18.0,
        "anti_chase_score": 18.0,
        "pullback_quality_score": 15.0,
        "breakout_compression_score": 6.0,
        "sympathy_score": 0,
        "theme": null,
        "halt_risk_score": 0,
        "market_regime": "NEUTRAL",
        "reasons": [
          "spread_tight",
          "dollar_volume_too_low",
          "weak_rvol",
          "vwap_controlled",
          "not_chasing_vwap_controlled",
          "near_vwap_pullback_zone",
          "breakout_not_overextended"
        ],
        "hard_blocks": [],
        "quality_gate_status": "DASHBOARD_ONLY",
        "quality_gate_blocks": [
          "base_status_not_trade_eligible:NO_TRADE",
          "dollar_volume_below_1m"
        ]
      }
    },
    {
      "ticker": "NIO",
      "status": "WATCH_ONLY",
      "quality_gate_status": "DASHBOARD_ONLY",
      "advanced_quality": {
        "advanced_quality_score": 72.0,
        "spread_pct": 0.3384,
        "dollar_volume": 305916.0,
        "spread_score": 15.0,
        "liquidity_score": 0.0,
        "rvol_quality_score": 2.0,
        "vwap_control_score": 18.0,
        "anti_chase_score": 13.0,
        "pullback_quality_score": 15.0,
        "breakout_compression_score": 6.0,
        "sympathy_score": 3,
        "theme": "ev",
        "halt_risk_score": 0,
        "market_regime": "NEUTRAL",
        "reasons": [
          "spread_tight",
          "dollar_volume_too_low",
          "weak_rvol",
          "vwap_controlled",
          "not_chasing_vwap_controlled",
          "volume_fading",
          "near_vwap_pullback_zone",
          "breakout_not_overextended"
        ],
        "hard_blocks": [],
        "quality_gate_status": "DASHBOARD_ONLY",
        "quality_gate_blocks": [
          "base_status_not_trade_eligible:WATCH_ONLY",
          "dollar_volume_below_1m"
        ]
      }
    },
    {
      "ticker": "DKNG",
      "status": "ALERT_ONLY",
      "quality_gate_status": "DASHBOARD_ONLY",
      "advanced_quality": {
        "advanced_quality_score": 71.0,
        "spread_pct": 0.8151,
        "dollar_volume": 172637.17,
        "spread_score": 12.0,
        "liquidity_score": 0.0,
        "rvol_quality_score": 2.0,
        "vwap_control_score": 18.0,
        "anti_chase_score": 18.0,
        "pullback_quality_score": 15.0,
        "breakout_compression_score": 6.0,
        "sympathy_score": 0,
        "theme": null,
        "halt_risk_score": 0,
        "market_regime": "NEUTRAL",
        "reasons": [
          "spread_acceptable",
          "dollar_volume_too_low",
          "weak_rvol",
          "vwap_controlled",
          "not_chasing_vwap_controlled",
          "near_vwap_pullback_zone",
          "breakout_not_overextended"
        ],
        "hard_blocks": [],
        "quality_gate_status": "DASHBOARD_ONLY",
        "quality_gate_blocks": [
          "base_status_not_trade_eligible:ALERT_ONLY",
          "dollar_volume_below_1m"
        ]
      }
    },
    {
      "ticker": "ENVX",
      "status": "WATCH_ONLY",
      "quality_gate_status": "DASHBOARD_ONLY",
      "advanced_quality": {
        "advanced_quality_score": 71.0,
        "spread_pct": 0.5013,
        "dollar_volume": 65857.74,
        "spread_score": 12.0,
        "liquidity_score": 0.0,
        "rvol_quality_score": 2.0,
        "vwap_control_score": 18.0,
        "anti_chase_score": 18.0,
        "pullback_quality_score": 15.0,
        "breakout_compression_score": 6.0,
        "sympathy_score": 0,
        "theme": null,
        "halt_risk_score": 0,
        "market_regime": "NEUTRAL",
        "reasons": [
          "spread_acceptable",
          "dollar_volume_too_low",
          "weak_rvol",
          "vwap_controlled",
          "not_chasing_vwap_controlled",
          "near_vwap_pullback_zone",
          "breakout_not_overextended"
        ],
        "hard_blocks": [],
        "quality_gate_status": "DASHBOARD_ONLY",
        "quality_gate_blocks": [
          "base_status_not_trade_eligible:WATCH_ONLY",
          "dollar_volume_below_1m"
        ]
      }
    },
    {
      "ticker": "DDOG",
      "status": "WATCH_ONLY",
      "quality_gate_status": "DASHBOARD_ONLY",
      "advanced_quality": {
        "advanced_quality_score": 71.0,
        "spread_pct": 0.6231,
        "dollar_volume": 53096.1,
        "spread_score": 12.0,
        "liquidity_score": 0.0,
        "rvol_quality_score": 2.0,
        "vwap_control_score": 18.0,
        "anti_chase_score": 18.0,
        "pullback_quality_score": 15.0,
        "breakout_compression_score": 6.0,
        "sympathy_score": 0,
        "theme": null,
        "halt_risk_score": 0,
        "market_regime": "NEUTRAL",
        "reasons": [
          "spread_acceptable",
          "dollar_volume_too_low",
          "weak_rvol",
          "vwap_controlled",
          "not_chasing_vwap_controlled",
          "near_vwap_pullback_zone",
          "breakout_not_overextended"
        ],
        "hard_blocks": [],
        "quality_gate_status": "DASHBOARD_ONLY",
        "quality_gate_blocks": [
          "base_status_not_trade_eligible:WATCH_ONLY",
          "dollar_volume_below_1m"
        ]
      }
    },
    {
      "ticker": "ZS",
      "status": "WATCH_ONLY",
      "quality_gate_status": "DASHBOARD_ONLY",
      "advanced_quality": {
        "advanced_quality_score": 69.0,
        "spread_pct": 0.2845,
        "dollar_volume": 497024.0,
        "spread_score": 15.0,
        "liquidity_score": 0.0,
        "rvol_quality_score": 2.0,
        "vwap_control_score": 18.0,
        "anti_chase_score": 13.0,
        "pullback_quality_score": 15.0,
        "breakout_compression_score": 6.0,
        "sympathy_score": 0,
        "theme": null,
        "halt_risk_score": 0,
        "market_regime": "NEUTRAL",
        "reasons": [
          "spread_tight",
          "dollar_volume_too_low",
          "weak_rvol",
          "vwap_controlled",
          "not_chasing_vwap_controlled",
          "volume_fading",
          "near_vwap_pullback_zone",
          "breakout_not_overextended"
        ],
        "hard_blocks": [],
        "quality_gate_status": "DASHBOARD_ONLY",
        "quality_gate_blocks": [
          "base_status_not_trade_eligible:WATCH_ONLY",
          "dollar_volume_below_1m"
        ]
      }
    },
    {
      "ticker": "OXY",
      "status": "WATCH_ONLY",
      "quality_gate_status": "DASHBOARD_ONLY",
      "advanced_quality": {
        "advanced_quality_score": 69.0,
        "spread_pct": 0.2011,
        "dollar_volume": 887797.52,
        "spread_score": 15.0,
        "liquidity_score": 0.0,
        "rvol_quality_score": 2.0,
        "vwap_control_score": 18.0,
        "anti_chase_score": 13.0,
        "pullback_quality_score": 15.0,
        "breakout_compression_score": 6.0,
        "sympathy_score": 0,
        "theme": null,
        "halt_risk_score": 0,
        "market_regime": "NEUTRAL",
        "reasons": [
          "spread_tight",
          "dollar_volume_too_low",
          "weak_rvol",
          "vwap_controlled",
          "not_chasing_vwap_controlled",
          "volume_fading",
          "near_vwap_pullback_zone",
          "breakout_not_overextended"
        ],
        "hard_blocks": [],
        "quality_gate_status": "DASHBOARD_ONLY",
        "quality_gate_blocks": [
          "base_status_not_trade_eligible:WATCH_ONLY",
          "dollar_volume_below_1m"
        ]
      }
    },
    {
      "ticker": "SMCI",
      "status": "WATCH_ONLY",
      "quality_gate_status": "DASHBOARD_ONLY",
      "advanced_quality": {
        "advanced_quality_score": 69.0,
        "spread_pct": 0.2594,
        "dollar_volume": 576189.92,
        "spread_score": 15.0,
        "liquidity_score": 0.0,
        "rvol_quality_score": 2.0,
        "vwap_control_score": 18.0,
        "anti_chase_score": 13.0,
        "pullback_quality_score": 15.0,
        "breakout_compression_score": 6.0,
        "sympathy_score": 0,
        "theme": null,
        "halt_risk_score": 0,
        "market_regime": "NEUTRAL",
        "reasons": [
          "spread_tight",
          "dollar_volume_too_low",
          "weak_rvol",
          "vwap_controlled",
          "not_chasing_vwap_controlled",
          "volume_fading",
          "near_vwap_pullback_zone",
          "breakout_not_overextended"
        ],
        "hard_blocks": [],
        "quality_gate_status": "DASHBOARD_ONLY",
        "quality_gate_blocks": [
          "base_status_not_trade_eligible:WATCH_ONLY",
          "dollar_volume_below_1m"
        ]
      }
    },
    {
      "ticker": "OPEN",
      "status": "WATCH_ONLY",
      "quality_gate_status": "DASHBOARD_ONLY",
      "advanced_quality": {
        "advanced_quality_score": 69.0,
        "spread_pct": 0.2334,
        "dollar_volume": 194063.37,
        "spread_score": 15.0,
        "liquidity_score": 0.0,
        "rvol_quality_score": 2.0,
        "vwap_control_score": 18.0,
        "anti_chase_score": 13.0,
        "pullback_quality_score": 15.0,
        "breakout_compression_score": 6.0,
        "sympathy_score": 0,
        "theme": null,
        "halt_risk_score": 0,
        "market_regime": "NEUTRAL",
        "reasons": [
          "spread_tight",
          "dollar_volume_too_low",
          "weak_rvol",
          "vwap_controlled",
          "not_chasing_vwap_controlled",
          "volume_fading",
          "near_vwap_pullback_zone",
          "breakout_not_overextended"
        ],
        "hard_blocks": [],
        "quality_gate_status": "DASHBOARD_ONLY",
        "quality_gate_blocks": [
          "base_status_not_trade_eligible:WATCH_ONLY",
          "dollar_volume_below_1m"
        ]
      }
    },
    {
      "ticker": "SNAP",
      "status": "WATCH_ONLY",
      "quality_gate_status": "DASHBOARD_ONLY",
      "advanced_quality": {
        "advanced_quality_score": 66.0,
        "spread_pct": 0.7042,
        "dollar_volume": 339525.27,
        "spread_score": 12.0,
        "liquidity_score": 0.0,
        "rvol_quality_score": 2.0,
        "vwap_control_score": 18.0,
        "anti_chase_score": 13.0,
        "pullback_quality_score": 15.0,
        "breakout_compression_score": 6.0,
        "sympathy_score": 0,
        "theme": null,
        "halt_risk_score": 0,
        "market_regime": "NEUTRAL",
        "reasons": [
          "spread_acceptable",
          "dollar_volume_too_low",
          "weak_rvol",
          "vwap_controlled",
          "not_chasing_vwap_controlled",
          "volume_fading",
          "near_vwap_pullback_zone",
          "breakout_not_overextended"
        ],
        "hard_blocks": [],
        "quality_gate_status": "DASHBOARD_ONLY",
        "quality_gate_blocks": [
          "base_status_not_trade_eligible:WATCH_ONLY",
          "dollar_volume_below_1m"
        ]
      }
    },
    {
      "ticker": "DAL",
      "status": "WATCH_ONLY",
      "quality_gate_status": "DASHBOARD_ONLY",
      "advanced_quality": {
        "advanced_quality_score": 62.0,
        "spread_pct": 1.6795,
        "dollar_volume": 184005.0,
        "spread_score": 0.0,
        "liquidity_score": 0.0,
        "rvol_quality_score": 2.0,
        "vwap_control_score": 18.0,
        "anti_chase_score": 18.0,
        "pullback_quality_score": 15.0,
        "breakout_compression_score": 6.0,
        "sympathy_score": 3,
        "theme": "travel_reopen",
        "halt_risk_score": 0,
        "market_regime": "NEUTRAL",
        "reasons": [
          "spread_too_wide",
          "dollar_volume_too_low",
          "weak_rvol",
          "vwap_controlled",
          "not_chasing_vwap_controlled",
          "near_vwap_pullback_zone",
          "breakout_not_overextended"
        ],
        "hard_blocks": [],
        "quality_gate_status": "DASHBOARD_ONLY",
        "quality_gate_blocks": [
          "base_status_not_trade_eligible:WATCH_ONLY",
          "spread_above_1_5",
          "dollar_volume_below_1m"
        ]
      }
    },
    {
      "ticker": "META",
      "status": "WATCH_ONLY",
      "quality_gate_status": "DASHBOARD_ONLY",
      "advanced_quality": {
        "advanced_quality_score": 52.0,
        "spread_pct": 0.1473,
        "dollar_volume": 7539091.5,
        "spread_score": 15.0,
        "liquidity_score": 12.0,
        "rvol_quality_score": 2.0,
        "vwap_control_score": 0.0,
        "anti_chase_score": 15.0,
        "pullback_quality_score": 1.0,
        "breakout_compression_score": 4.0,
        "sympathy_score": 3,
        "theme": "mega_cap_ai",
        "halt_risk_score": 0,
        "market_regime": "NEUTRAL",
        "reasons": [
          "spread_tight",
          "good_dollar_volume",
          "weak_rvol",
          "below_vwap",
          "below_vwap_no_pullback_entry",
          "breakout_volume_acceleration"
        ],
        "hard_blocks": [],
        "quality_gate_status": "DASHBOARD_ONLY",
        "quality_gate_blocks": [
          "base_status_not_trade_eligible:WATCH_ONLY"
        ]
      }
    },
    {
      "ticker": "GOOG",
      "status": "WATCH_ONLY",
      "quality_gate_status": "DASHBOARD_ONLY",
      "advanced_quality": {
        "advanced_quality_score": 52.0,
        "spread_pct": 0.1113,
        "dollar_volume": 12073691.56,
        "spread_score": 15.0,
        "liquidity_score": 12.0,
        "rvol_quality_score": 2.0,
        "vwap_control_score": 0.0,
        "anti_chase_score": 15.0,
        "pullback_quality_score": 1.0,
        "breakout_compression_score": 4.0,
        "sympathy_score": 3,
        "theme": "mega_cap_ai",
        "halt_risk_score": 0,
        "market_regime": "NEUTRAL",
        "reasons": [
          "spread_tight",
          "good_dollar_volume",
          "weak_rvol",
          "below_vwap",
          "below_vwap_no_pullback_entry",
          "breakout_volume_acceleration"
        ],
        "hard_blocks": [],
        "quality_gate_status": "DASHBOARD_ONLY",
        "quality_gate_blocks": [
          "base_status_not_trade_eligible:WATCH_ONLY"
        ]
      }
    },
    {
      "ticker": "AMZN",
      "status": "NO_TRADE",
      "quality_gate_status": "DASHBOARD_ONLY",
      "advanced_quality": {
        "advanced_quality_score": 52.0,
        "spread_pct": 0.0566,
        "dollar_volume": 7044479.16,
        "spread_score": 15.0,
        "liquidity_score": 12.0,
        "rvol_quality_score": 2.0,
        "vwap_control_score": 0.0,
        "anti_chase_score": 15.0,
        "pullback_quality_score": 1.0,
        "breakout_compression_score": 4.0,
        "sympathy_score": 3,
        "theme": "mega_cap_ai",
        "halt_risk_score": 0,
        "market_regime": "NEUTRAL",
        "reasons": [
          "spread_tight",
          "good_dollar_volume",
          "weak_rvol",
          "below_vwap",
          "below_vwap_no_pullback_entry",
          "breakout_volume_acceleration"
        ],
        "hard_blocks": [],
        "quality_gate_status": "DASHBOARD_ONLY",
        "quality_gate_blocks": [
          "base_status_not_trade_eligible:NO_TRADE"
        ]
      }
    },
    {
      "ticker": "RKLB",
      "status": "NO_TRADE",
      "quality_gate_status": "DASHBOARD_ONLY",
      "advanced_quality": {
        "advanced_quality_score": 48.0,
        "spread_pct": 0.4598,
        "dollar_volume": 5052213.81,
        "spread_score": 15.0,
        "liquidity_score": 12.0,
        "rvol_quality_score": 2.0,
        "vwap_control_score": 0.0,
        "anti_chase_score": 15.0,
        "pullback_quality_score": 1.0,
        "breakout_compression_score": 0,
        "sympathy_score": 3,
        "theme": "space_air",
        "halt_risk_score": 0,
        "market_regime": "NEUTRAL",
        "reasons": [
          "spread_tight",
          "good_dollar_volume",
          "weak_rvol",
          "below_vwap",
          "below_vwap_no_pullback_entry"
        ],
        "hard_blocks": [],
        "quality_gate_status": "DASHBOARD_ONLY",
        "quality_gate_blocks": [
          "base_status_not_trade_eligible:NO_TRADE"
        ]
      }
    },
    {
      "ticker": "BABA",
      "status": "NO_TRADE",
      "quality_gate_status": "DASHBOARD_ONLY",
      "advanced_quality": {
        "advanced_quality_score": 44.0,
        "spread_pct": 0.1573,
        "dollar_volume": 2008737.2,
        "spread_score": 15.0,
        "liquidity_score": 7.0,
        "rvol_quality_score": 2.0,
        "vwap_control_score": 0.0,
        "anti_chase_score": 15.0,
        "pullback_quality_score": 1.0,
        "breakout_compression_score": 4.0,
        "sympathy_score": 0,
        "theme": null,
        "halt_risk_score": 0,
        "market_regime": "NEUTRAL",
        "reasons": [
          "spread_tight",
          "thin_but_tradeable_dollar_volume",
          "weak_rvol",
          "below_vwap",
          "below_vwap_no_pullback_entry",
          "breakout_volume_acceleration"
        ],
        "hard_blocks": [],
        "quality_gate_status": "DASHBOARD_ONLY",
        "quality_gate_blocks": [
          "base_status_not_trade_eligible:NO_TRADE"
        ]
      }
    },
    {
      "ticker": "MSTR",
      "status": "NO_TRADE",
      "quality_gate_status": "DASHBOARD_ONLY",
      "advanced_quality": {
        "advanced_quality_score": 43.0,
        "spread_pct": 0.299,
        "dollar_volume": 2525048.1,
        "spread_score": 15.0,
        "liquidity_score": 7.0,
        "rvol_quality_score": 2.0,
        "vwap_control_score": 0.0,
        "anti_chase_score": 15.0,
        "pullback_quality_score": 1.0,
        "breakout_compression_score": 0,
        "sympathy_score": 3,
        "theme": "crypto",
        "halt_risk_score": 0,
        "market_regime": "NEUTRAL",
        "reasons": [
          "spread_tight",
          "thin_but_tradeable_dollar_volume",
          "weak_rvol",
          "below_vwap",
          "below_vwap_no_pullback_entry"
        ],
        "hard_blocks": [],
        "quality_gate_status": "DASHBOARD_ONLY",
        "quality_gate_blocks": [
          "base_status_not_trade_eligible:NO_TRADE"
        ]
      }
    },
    {
      "ticker": "MSFT",
      "status": "NO_TRADE",
      "quality_gate_status": "DASHBOARD_ONLY",
      "advanced_quality": {
        "advanced_quality_score": 43.0,
        "spread_pct": 0.0189,
        "dollar_volume": 8750083.2,
        "spread_score": 15.0,
        "liquidity_score": 12.0,
        "rvol_quality_score": 2.0,
        "vwap_control_score": 0.0,
        "anti_chase_score": 10.0,
        "pullback_quality_score": 1.0,
        "breakout_compression_score": 0,
        "sympathy_score": 3,
        "theme": "mega_cap_ai",
        "halt_risk_score": 0,
        "market_regime": "NEUTRAL",
        "reasons": [
          "spread_tight",
          "good_dollar_volume",
          "weak_rvol",
          "below_vwap",
          "volume_fading",
          "below_vwap_no_pullback_entry"
        ],
        "hard_blocks": [],
        "quality_gate_status": "DASHBOARD_ONLY",
        "quality_gate_blocks": [
          "base_status_not_trade_eligible:NO_TRADE"
        ]
      }
    },
    {
      "ticker": "CRM",
      "status": "WATCH_ONLY",
      "quality_gate_status": "DASHBOARD_ONLY",
      "advanced_quality": {
        "advanced_quality_score": 40.25,
        "spread_pct": 0.1112,
        "dollar_volume": 1145597.54,
        "spread_score": 15.0,
        "liquidity_score": 7.0,
        "rvol_quality_score": 2.0,
        "vwap_control_score": 0.0,
        "anti_chase_score": 15.0,
        "pullback_quality_score": 1.0,
        "breakout_compression_score": 4.0,
        "sympathy_score": 0,
        "theme": null,
        "halt_risk_score": 15.0,
        "market_regime": "NEUTRAL",
        "reasons": [
          "spread_tight",
          "thin_but_tradeable_dollar_volume",
          "weak_rvol",
          "below_vwap",
          "below_vwap_no_pullback_entry",
          "breakout_volume_acceleration",
          "volume_ignition_halt_risk"
        ],
        "hard_blocks": [],
        "quality_gate_status": "DASHBOARD_ONLY",
        "quality_gate_blocks": [
          "base_status_not_trade_eligible:WATCH_ONLY"
        ]
      }
    },
    {
      "ticker": "SOUN",
      "status": "WATCH_ONLY",
      "quality_gate_status": "DASHBOARD_ONLY",
      "advanced_quality": {
        "advanced_quality_score": 40.0,
        "spread_pct": 0.2401,
        "dollar_volume": 155392.64,
        "spread_score": 15.0,
        "liquidity_score": 0.0,
        "rvol_quality_score": 2.0,
        "vwap_control_score": 0.0,
        "anti_chase_score": 15.0,
        "pullback_quality_score": 1.0,
        "breakout_compression_score": 4.0,
        "sympathy_score": 3,
        "theme": "small_cap_ai",
        "halt_risk_score": 0,
        "market_regime": "NEUTRAL",
        "reasons": [
          "spread_tight",
          "dollar_volume_too_low",
          "weak_rvol",
          "below_vwap",
          "below_vwap_no_pullback_entry",
          "breakout_volume_acceleration"
        ],
        "hard_blocks": [],
        "quality_gate_status": "DASHBOARD_ONLY",
        "quality_gate_blocks": [
          "base_status_not_trade_eligible:WATCH_ONLY",
          "dollar_volume_below_1m"
        ]
      }
    },
    {
      "ticker": "NFLX",
      "status": "NO_TRADE",
      "quality_gate_status": "DASHBOARD_ONLY",
      "advanced_quality": {
        "advanced_quality_score": 40.0,
        "spread_pct": 0.0111,
        "dollar_volume": 3656689.51,
        "spread_score": 15.0,
        "liquidity_score": 7.0,
        "rvol_quality_score": 2.0,
        "vwap_control_score": 0.0,
        "anti_chase_score": 15.0,
        "pullback_quality_score": 1.0,
        "breakout_compression_score": 0,
        "sympathy_score": 0,
        "theme": null,
        "halt_risk_score": 0,
        "market_regime": "NEUTRAL",
        "reasons": [
          "spread_tight",
          "thin_but_tradeable_dollar_volume",
          "weak_rvol",
          "below_vwap",
          "below_vwap_no_pullback_entry"
        ],
        "hard_blocks": [],
        "quality_gate_status": "DASHBOARD_ONLY",
        "quality_gate_blocks": [
          "base_status_not_trade_eligible:NO_TRADE"
        ]
      }
    },
    {
      "ticker": "SNOW",
      "status": "NO_TRADE",
      "quality_gate_status": "DASHBOARD_ONLY",
      "advanced_quality": {
        "advanced_quality_score": 40.0,
        "spread_pct": 0.3753,
        "dollar_volume": 1734753.91,
        "spread_score": 15.0,
        "liquidity_score": 7.0,
        "rvol_quality_score": 2.0,
        "vwap_control_score": 0.0,
        "anti_chase_score": 15.0,
        "pullback_quality_score": 1.0,
        "breakout_compression_score": 0,
        "sympathy_score": 0,
        "theme": null,
        "halt_risk_score": 0,
        "market_regime": "NEUTRAL",
        "reasons": [
          "spread_tight",
          "thin_but_tradeable_dollar_volume",
          "weak_rvol",
          "below_vwap",
          "below_vwap_no_pullback_entry"
        ],
        "hard_blocks": [],
        "quality_gate_status": "DASHBOARD_ONLY",
        "quality_gate_blocks": [
          "base_status_not_trade_eligible:NO_TRADE"
        ]
      }
    },
    {
      "ticker": "UPST",
      "status": "NO_TRADE",
      "quality_gate_status": "DASHBOARD_ONLY",
      "advanced_quality": {
        "advanced_quality_score": 37.0,
        "spread_pct": 0.3591,
        "dollar_volume": 201325.68,
        "spread_score": 15.0,
        "liquidity_score": 0.0,
        "rvol_quality_score": 2.0,
        "vwap_control_score": 0.0,
        "anti_chase_score": 15.0,
        "pullback_quality_score": 1.0,
        "breakout_compression_score": 4.0,
        "sympathy_score": 0,
        "theme": "fintech",
        "halt_risk_score": 0,
        "market_regime": "NEUTRAL",
        "reasons": [
          "spread_tight",
          "dollar_volume_too_low",
          "weak_rvol",
          "below_vwap",
          "below_vwap_no_pullback_entry",
          "breakout_volume_acceleration"
        ],
        "hard_blocks": [],
        "quality_gate_status": "DASHBOARD_ONLY",
        "quality_gate_blocks": [
          "base_status_not_trade_eligible:NO_TRADE",
          "dollar_volume_below_1m"
        ]
      }
    },
    {
      "ticker": "QBTS",
      "status": "NO_TRADE",
      "quality_gate_status": "DASHBOARD_ONLY",
      "advanced_quality": {
        "advanced_quality_score": 37.0,
        "spread_pct": 0.526,
        "dollar_volume": 631274.8,
        "spread_score": 12.0,
        "liquidity_score": 0.0,
        "rvol_quality_score": 2.0,
        "vwap_control_score": 0.0,
        "anti_chase_score": 15.0,
        "pullback_quality_score": 1.0,
        "breakout_compression_score": 4.0,
        "sympathy_score": 3,
        "theme": "quantum",
        "halt_risk_score": 0,
        "market_regime": "NEUTRAL",
        "reasons": [
          "spread_acceptable",
          "dollar_volume_too_low",
          "weak_rvol",
          "below_vwap",
          "below_vwap_no_pullback_entry",
          "breakout_volume_acceleration"
        ],
        "hard_blocks": [],
        "quality_gate_status": "DASHBOARD_ONLY",
        "quality_gate_blocks": [
          "base_status_not_trade_eligible:NO_TRADE",
          "dollar_volume_below_1m"
        ]
      }
    },
    {
      "ticker": "LUNR",
      "status": "NO_TRADE",
      "quality_gate_status": "DASHBOARD_ONLY",
      "advanced_quality": {
        "advanced_quality_score": 37.0,
        "spread_pct": 0.8175,
        "dollar_volume": 709588.19,
        "spread_score": 12.0,
        "liquidity_score": 0.0,
        "rvol_quality_score": 2.0,
        "vwap_control_score": 0.0,
        "anti_chase_score": 15.0,
        "pullback_quality_score": 1.0,
        "breakout_compression_score": 4.0,
        "sympathy_score": 3,
        "theme": "space_air",
        "halt_risk_score": 0,
        "market_regime": "NEUTRAL",
        "reasons": [
          "spread_acceptable",
          "dollar_volume_too_low",
          "weak_rvol",
          "below_vwap",
          "below_vwap_no_pullback_entry",
          "breakout_volume_acceleration"
        ],
        "hard_blocks": [],
        "quality_gate_status": "DASHBOARD_ONLY",
        "quality_gate_blocks": [
          "base_status_not_trade_eligible:NO_TRADE",
          "dollar_volume_below_1m"
        ]
      }
    },
    {
      "ticker": "ACHR",
      "status": "NO_TRADE",
      "quality_gate_status": "DASHBOARD_ONLY",
      "advanced_quality": {
        "advanced_quality_score": 37.0,
        "spread_pct": 0.6723,
        "dollar_volume": 164060.96,
        "spread_score": 12.0,
        "liquidity_score": 0.0,
        "rvol_quality_score": 2.0,
        "vwap_control_score": 0.0,
        "anti_chase_score": 15.0,
        "pullback_quality_score": 1.0,
        "breakout_compression_score": 4.0,
        "sympathy_score": 3,
        "theme": "space_air",
        "halt_risk_score": 0,
        "market_regime": "NEUTRAL",
        "reasons": [
          "spread_acceptable",
          "dollar_volume_too_low",
          "weak_rvol",
          "below_vwap",
          "below_vwap_no_pullback_entry",
          "breakout_volume_acceleration"
        ],
        "hard_blocks": [],
        "quality_gate_status": "DASHBOARD_ONLY",
        "quality_gate_blocks": [
          "base_status_not_trade_eligible:NO_TRADE",
          "dollar_volume_below_1m"
        ]
      }
    },
    {
      "ticker": "BBAI",
      "status": "NO_TRADE",
      "quality_gate_status": "DASHBOARD_ONLY",
      "advanced_quality": {
        "advanced_quality_score": 37.0,
        "spread_pct": 0.5115,
        "dollar_volume": 210037.52,
        "spread_score": 12.0,
        "liquidity_score": 0.0,
        "rvol_quality_score": 2.0,
        "vwap_control_score": 0.0,
        "anti_chase_score": 15.0,
        "pullback_quality_score": 1.0,
        "breakout_compression_score": 4.0,
        "sympathy_score": 3,
        "theme": "small_cap_ai",
        "halt_risk_score": 0,
        "market_regime": "NEUTRAL",
        "reasons": [
          "spread_acceptable",
          "dollar_volume_too_low",
          "weak_rvol",
          "below_vwap",
          "below_vwap_no_pullback_entry",
          "breakout_volume_acceleration"
        ],
        "hard_blocks": [],
        "quality_gate_status": "DASHBOARD_ONLY",
        "quality_gate_blocks": [
          "base_status_not_trade_eligible:NO_TRADE",
          "dollar_volume_below_1m"
        ]
      }
    },
    {
      "ticker": "LI",
      "status": "NO_TRADE",
      "quality_gate_status": "DASHBOARD_ONLY",
      "advanced_quality": {
        "advanced_quality_score": 36.25,
        "spread_pct": 0.0598,
        "dollar_volume": 124830.77,
        "spread_score": 15.0,
        "liquidity_score": 0.0,
        "rvol_quality_score": 2.0,
        "vwap_control_score": 0.0,
        "anti_chase_score": 15.0,
        "pullback_quality_score": 1.0,
        "breakout_compression_score": 4.0,
        "sympathy_score": 3,
        "theme": "ev",
        "halt_risk_score": 15.0,
        "market_regime": "NEUTRAL",
        "reasons": [
          "spread_tight",
          "dollar_volume_too_low",
          "weak_rvol",
          "below_vwap",
          "below_vwap_no_pullback_entry",
          "breakout_volume_acceleration",
          "volume_ignition_halt_risk"
        ],
        "hard_blocks": [],
        "quality_gate_status": "DASHBOARD_ONLY",
        "quality_gate_blocks": [
          "base_status_not_trade_eligible:NO_TRADE",
          "dollar_volume_below_1m"
        ]
      }
    },
    {
      "ticker": "GME",
      "status": "NO_TRADE",
      "quality_gate_status": "DASHBOARD_ONLY",
      "advanced_quality": {
        "advanced_quality_score": 36.25,
        "spread_pct": 0.0913,
        "dollar_volume": 487997.7,
        "spread_score": 15.0,
        "liquidity_score": 0.0,
        "rvol_quality_score": 2.0,
        "vwap_control_score": 0.0,
        "anti_chase_score": 15.0,
        "pullback_quality_score": 1.0,
        "breakout_compression_score": 4.0,
        "sympathy_score": 3,
        "theme": "meme_retail",
        "halt_risk_score": 15.0,
        "market_regime": "NEUTRAL",
        "reasons": [
          "spread_tight",
          "dollar_volume_too_low",
          "weak_rvol",
          "below_vwap",
          "below_vwap_no_pullback_entry",
          "breakout_volume_acceleration",
          "volume_ignition_halt_risk"
        ],
        "hard_blocks": [],
        "quality_gate_status": "DASHBOARD_ONLY",
        "quality_gate_blocks": [
          "base_status_not_trade_eligible:NO_TRADE",
          "dollar_volume_below_1m"
        ]
      }
    },
    {
      "ticker": "CVX",
      "status": "NO_TRADE",
      "quality_gate_status": "DASHBOARD_ONLY",
      "advanced_quality": {
        "advanced_quality_score": 35.0,
        "spread_pct": 0.1275,
        "dollar_volume": 1363116.12,
        "spread_score": 15.0,
        "liquidity_score": 7.0,
        "rvol_quality_score": 2.0,
        "vwap_control_score": 0.0,
        "anti_chase_score": 10.0,
        "pullback_quality_score": 1.0,
        "breakout_compression_score": 0,
        "sympathy_score": 0,
        "theme": null,
        "halt_risk_score": 0,
        "market_regime": "NEUTRAL",
        "reasons": [
          "spread_tight",
          "thin_but_tradeable_dollar_volume",
          "weak_rvol",
          "below_vwap",
          "volume_fading",
          "below_vwap_no_pullback_entry"
        ],
        "hard_blocks": [],
        "quality_gate_status": "DASHBOARD_ONLY",
        "quality_gate_blocks": [
          "base_status_not_trade_eligible:NO_TRADE"
        ]
      }
    },
    {
      "ticker": "SHOP",
      "status": "WATCH_ONLY",
      "quality_gate_status": "DASHBOARD_ONLY",
      "advanced_quality": {
        "advanced_quality_score": 33.25,
        "spread_pct": 0.1074,
        "dollar_volume": 417485.89,
        "spread_score": 15.0,
        "liquidity_score": 0.0,
        "rvol_quality_score": 2.0,
        "vwap_control_score": 0.0,
        "anti_chase_score": 15.0,
        "pullback_quality_score": 1.0,
        "breakout_compression_score": 4.0,
        "sympathy_score": 0,
        "theme": null,
        "halt_risk_score": 15.0,
        "market_regime": "NEUTRAL",
        "reasons": [
          "spread_tight",
          "dollar_volume_too_low",
          "weak_rvol",
          "below_vwap",
          "below_vwap_no_pullback_entry",
          "breakout_volume_acceleration",
          "volume_ignition_halt_risk"
        ],
        "hard_blocks": [],
        "quality_gate_status": "DASHBOARD_ONLY",
        "quality_gate_blocks": [
          "base_status_not_trade_eligible:WATCH_ONLY",
          "dollar_volume_below_1m"
        ]
      }
    },
    {
      "ticker": "CELH",
      "status": "NO_TRADE",
      "quality_gate_status": "DASHBOARD_ONLY",
      "advanced_quality": {
        "advanced_quality_score": 33.0,
        "spread_pct": 0.3045,
        "dollar_volume": 57751.07,
        "spread_score": 15.0,
        "liquidity_score": 0.0,
        "rvol_quality_score": 2.0,
        "vwap_control_score": 0.0,
        "anti_chase_score": 15.0,
        "pullback_quality_score": 1.0,
        "breakout_compression_score": 0,
        "sympathy_score": 0,
        "theme": null,
        "halt_risk_score": 0,
        "market_regime": "NEUTRAL",
        "reasons": [
          "spread_tight",
          "dollar_volume_too_low",
          "weak_rvol",
          "below_vwap",
          "below_vwap_no_pullback_entry"
        ],
        "hard_blocks": [],
        "quality_gate_status": "DASHBOARD_ONLY",
        "quality_gate_blocks": [
          "base_status_not_trade_eligible:NO_TRADE",
          "dollar_volume_below_1m"
        ]
      }
    },
    {
      "ticker": "WULF",
      "status": "NO_TRADE",
      "quality_gate_status": "DASHBOARD_ONLY",
      "advanced_quality": {
        "advanced_quality_score": 31.0,
        "spread_pct": 0.2362,
        "dollar_volume": 355449.64,
        "spread_score": 15.0,
        "liquidity_score": 0.0,
        "rvol_quality_score": 2.0,
        "vwap_control_score": 0.0,
        "anti_chase_score": 10.0,
        "pullback_quality_score": 1.0,
        "breakout_compression_score": 0,
        "sympathy_score": 3,
        "theme": "crypto",
        "halt_risk_score": 0,
        "market_regime": "NEUTRAL",
        "reasons": [
          "spread_tight",
          "dollar_volume_too_low",
          "weak_rvol",
          "below_vwap",
          "volume_fading",
          "below_vwap_no_pullback_entry"
        ],
        "hard_blocks": [],
        "quality_gate_status": "DASHBOARD_ONLY",
        "quality_gate_blocks": [
          "base_status_not_trade_eligible:NO_TRADE",
          "dollar_volume_below_1m"
        ]
      }
    },
    {
      "ticker": "NET",
      "status": "NO_TRADE",
      "quality_gate_status": "DASHBOARD_ONLY",
      "advanced_quality": {
        "advanced_quality_score": 30.0,
        "spread_pct": 0.6093,
        "dollar_volume": 127810.61,
        "spread_score": 12.0,
        "liquidity_score": 0.0,
        "rvol_quality_score": 2.0,
        "vwap_control_score": 0.0,
        "anti_chase_score": 15.0,
        "pullback_quality_score": 1.0,
        "breakout_compression_score": 0,
        "sympathy_score": 0,
        "theme": null,
        "halt_risk_score": 0,
        "market_regime": "NEUTRAL",
        "reasons": [
          "spread_acceptable",
          "dollar_volume_too_low",
          "weak_rvol",
          "below_vwap",
          "below_vwap_no_pullback_entry"
        ],
        "hard_blocks": [],
        "quality_gate_status": "DASHBOARD_ONLY",
        "quality_gate_blocks": [
          "base_status_not_trade_eligible:NO_TRADE",
          "dollar_volume_below_1m"
        ]
      }
    }
  ],
  "safety": {
    "paper_only": true,
    "order_submission": false,
    "quality_gate_cannot_submit_orders": true,
    "disclaimer": "Quality scoring only. Not financial advice."
  }
}